{"file:///home/alice/kua-test/src/command-codes.hpp":{"language":"C++","code":11,"comment":0,"blank":3},"file:///home/alice/kua-test/src/kua.cpp":{"language":"C++","code":28,"comment":7,"blank":10},"file:///home/alice/kua-test/src/config-bundle.hpp":{"language":"C++","code":18,"comment":1,"blank":6},"file:///home/alice/kua-test/src/master.hpp":{"language":"C++","code":60,"comment":19,"blank":21},"file:///home/alice/kua-test/src/worker.hpp":{"language":"C++","code":48,"comment":0,"blank":22},"file:///home/alice/kua-test/src/client.cpp":{"language":"C++","code":255,"comment":18,"blank":56},"file:///home/alice/kua-test/src/tlv.hpp":{"language":"C++","code":14,"comment":0,"blank":3},"file:///home/alice/kua-test/src/store.hpp":{"language":"C++","code":16,"comment":0,"blank":8},"file:///home/alice/kua-test/src/auction.cpp":{"language":"C++","code":77,"comment":6,"blank":24},"file:///home/alice/kua-test/src/nlsr.cpp":{"language":"C++","code":72,"comment":0,"blank":20},"file:///home/alice/kua-test/src/worker.cpp":{"language":"C++","code":257,"comment":14,"blank":61},"file:///home/alice/kua-test/src/bucket.hpp":{"language":"C++","code":30,"comment":0,"blank":12},"file:///home/alice/kua-test/src/nlsr.hpp":{"language":"C++","code":34,"comment":0,"blank":11},"file:///home/alice/kua-test/src/auction.hpp":{"language":"C++","code":32,"comment":3,"blank":15},"file:///home/alice/kua-test/src/node-watcher.cpp":{"language":"C++","code":56,"comment":4,"blank":16},"file:///home/alice/kua-test/src/bidder.hpp":{"language":"C++","code":30,"comment":1,"blank":8},"file:///home/alice/kua-test/src/node-watcher.hpp":{"language":"C++","code":27,"comment":4,"blank":15},"file:///home/alice/kua-test/src/master.cpp":{"language":"C++","code":154,"comment":11,"blank":40},"file:///home/alice/kua-test/src/store-memory.hpp":{"language":"C++","code":41,"comment":0,"blank":8},"file:///home/alice/kua-test/src/bidder.cpp":{"language":"C++","code":151,"comment":1,"blank":32}}